ROA/ROA.cpython-38-x86_64-linux-gnu.so
ROA/__init__.py
ROA-1.8.dist-info/METADATA
ROA-1.8.dist-info/WHEEL
ROA-1.8.dist-info/top_level.txt
ROA-1.8.dist-info/LICENSE.txt
ROA-1.8.dist-info/RECORD
