Metadata-Version: 2.1
Name: ROA
Version: 1.8
Summary: A simple function to compute the running optimal average and effective no. of parameters.
Home-page: https://github.com/FergusDonnan/Running-Optimal-Average
Author: Fergus Donnan
License: UNKNOWN
Platform: UNKNOWN
Requires-Dist: numpy (>=1.19.2)
